asyncpg_typed/__init__.py
asyncpg_typed/py.typed
asyncpg_typed-0.1.3.dist-info/licenses/LICENSE
asyncpg_typed-0.1.3.dist-info/METADATA
asyncpg_typed-0.1.3.dist-info/WHEEL
asyncpg_typed-0.1.3.dist-info/top_level.txt
asyncpg_typed-0.1.3.dist-info/zip-safe
asyncpg_typed-0.1.3.dist-info/RECORD
