Metadata-Version: 2.4
Name: asyncpg_typed
Version: 0.1.3
Summary: Type-safe queries for asyncpg
Author-email: Levente Hunyadi <hunyadi@gmail.com>
Maintainer-email: Levente Hunyadi <hunyadi@gmail.com>
License-Expression: MIT
Project-URL: Homepage, https://github.com/hunyadi/asyncpg_typed
Project-URL: Source, https://github.com/hunyadi/asyncpg_typed
Keywords: asyncpg,typed,database-client,postgres
Classifier: Development Status :: 5 - Production/Stable
Classifier: Intended Audience :: Developers
Classifier: Operating System :: OS Independent
Classifier: Programming Language :: Python :: 3
Classifier: Programming Language :: Python :: 3.10
Classifier: Programming Language :: Python :: 3.11
Classifier: Programming Language :: Python :: 3.12
Classifier: Programming Language :: Python :: 3.13
Classifier: Programming Language :: Python :: 3.14
Classifier: Programming Language :: Python :: 3 :: Only
Classifier: Programming Language :: SQL
Classifier: Topic :: Database
Classifier: Topic :: Utilities
Classifier: Typing :: Typed
Requires-Python: >=3.10
License-File: LICENSE
Requires-Dist: asyncpg>=0.31
Requires-Dist: typing-extensions>=4.15; python_version < "3.11"
Provides-Extra: vector
Requires-Dist: asyncpg-vector>=0.1; extra == "vector"
Provides-Extra: dev
Requires-Dist: asyncpg-stubs>=0.31; extra == "dev"
Requires-Dist: build>=1.3; extra == "dev"
Requires-Dist: mypy>=1.19; extra == "dev"
Requires-Dist: ruff>=0.14; extra == "dev"
Dynamic: license-file
